setup.py
dj_bioinformatics_protein/__init__.py
dj_bioinformatics_protein/admin.py
dj_bioinformatics_protein/fields.py
dj_bioinformatics_protein/models.py
dj_bioinformatics_protein/tests.py
dj_bioinformatics_protein/validatiors.py
dj_bioinformatics_protein/views.py
dj_bioinformatics_protein.egg-info/PKG-INFO
dj_bioinformatics_protein.egg-info/SOURCES.txt
dj_bioinformatics_protein.egg-info/dependency_links.txt
dj_bioinformatics_protein.egg-info/top_level.txt
dj_bioinformatics_protein.egg-info/zip-safe
dj_bioinformatics_protein/migrations/0001_initial.py
dj_bioinformatics_protein/migrations/0001_initial_squashed_0006_auto_20170707_0908.py
dj_bioinformatics_protein/migrations/0002_auto_20170707_0908.py
dj_bioinformatics_protein/migrations/0002_remove_alignment_sha256.py
dj_bioinformatics_protein/migrations/0003_auto_20160227_0008.py
dj_bioinformatics_protein/migrations/0004_auto_20170621_1918.py
dj_bioinformatics_protein/migrations/0005_auto_20170627_2014.py
dj_bioinformatics_protein/migrations/0006_auto_20170707_0908.py
dj_bioinformatics_protein/migrations/__init__.py