Metadata-Version: 1.0
Name: dj-bioinformatics-protein
Version: 1.1.7
Summary: Django utilities and tools for protein storage and manipulation
Home-page: http://github.com/CyrusBiotechnology/dj-protein
Author: Peter Novotnak, Yifan Song
Author-email: peter@cyrusbio.com, yifan@cyrusbio.com
License: MIT
Platform: UNKNOWN
